fastai_ml/basics.py
fastai_ml-1.0.0.dist-info/LICENSE.txt
fastai_ml-1.0.0.dist-info/METADATA
fastai_ml-1.0.0.dist-info/WHEEL
fastai_ml-1.0.0.dist-info/top_level.txt
fastai_ml-1.0.0.dist-info/RECORD
