Metadata-Version: 2.1
Name: fastai-ml
Version: 1.0.0
Summary: A Python package to get helper functions for ML while using latest fastai.
Home-page: https://github.com/sbmalik/fastai-ml
Author: Subtain Tariq Malik
Author-email: m3si6ti@gmail.com
License: MIT
Platform: UNKNOWN
Requires-Dist: fastai
Requires-Dist: pandas
Requires-Dist: pandas-summary
